nautiluscli/__init__.py
nautiluscli/api.py
nautiluscli/cli.py
nautiluscli/embedding_model.py
nautiluscli/model.py
nautiluscli-0.5.2.dist-info/LICENSE
nautiluscli-0.5.2.dist-info/METADATA
nautiluscli-0.5.2.dist-info/WHEEL
nautiluscli-0.5.2.dist-info/entry_points.txt
nautiluscli-0.5.2.dist-info/RECORD
