Metadata-Version: 2.1
Name: nautiluscli
Version: 0.5.2
Summary: Command-line interface for NautilusDB
Author: NautilusDB
Author-email: contact@nautilusdb.com
Requires-Python: >=3.10,<4.0
Classifier: License :: OSI Approved :: Apache Software License
Classifier: Operating System :: OS Independent
Classifier: Programming Language :: Python :: 3
Classifier: Programming Language :: Python :: 3.10
Classifier: Programming Language :: Python :: 3.11
Classifier: Programming Language :: Python :: 3.12
Requires-Dist: api (>=0.0.7,<0.0.8)
Requires-Dist: click (>=8.1.7,<9.0.0)
Requires-Dist: lib (>=4.0.0,<5.0.0)
Requires-Dist: pydantic (>=2.4.2,<3.0.0)
Requires-Dist: requests (>=2.31.0,<3.0.0)
